{
  "generated_at": "2026-05-16 23:59 (台灣時間)",
  "date": "2026-05-16",
  "stats": {
    "settled": 91,
    "wins": 61,
    "win_rate": 67.0,
    "total_in": 1086.7,
    "total_pnl": 231.6,
    "roi": 21.3,
    "by_type": {
      "ML": {
        "wins": 24,
        "settled": 37,
        "win_rate": 64.9,
        "roi": -3.2
      },
      "RL": {
        "wins": 24,
        "settled": 34,
        "win_rate": 70.6,
        "roi": 38.0
      },
      "TOT": {
        "wins": 13,
        "settled": 20,
        "win_rate": 65.0,
        "roi": 45.9
      }
    }
  },
  "picks": [
    {
      "tier": "⭐ 穩定",
      "btype": "讓分",
      "away": "rangers",
      "home": "astros",
      "away_cn": "遊騎兵",
      "home_cn": "太空人",
      "bet_label": "太空人 讓分(+1.5)",
      "bk": "LowVig.ag",
      "bp": 1.76,
      "con_p": 1.734,
      "dv_p": 0.5525,
      "edge": 17.6,
      "conf": 76.9,
      "stake": 10.9,
      "model_p": 72.0,
      "away_sp": "Jacob deGrom",
      "home_sp": "Kai-Wei Teng",
      "away_era": 2.61,
      "home_era": 4.2,
      "away_fip": 2.31,
      "home_fip": null,
      "away_k9": 10.4,
      "home_k9": null,
      "away_avgip": 6.4,
      "home_avgip": null,
      "away_whip": 0.73,
      "home_whip": null,
      "away_rest": null,
      "home_rest": null,
      "away_rs": 3.0,
      "home_rs": null,
      "away_rpg": 3.97,
      "home_rpg": 4.59,
      "pred_away": 3.7,
      "pred_home": 4.2,
      "model_total": null,
      "market_total": null,
      "park_factor": null,
      "weather_factor": null,
      "ump_name": null,
      "ump_adj": null,
      "away_trend": 2.94,
      "home_trend": null,
      "line_clv": -0.99,
      "game_date": "2026-05-17",
      "game_time": "07:11",
      "sp_src": "probable",
      "home_hand": "R",
      "away_hand": "R",
      "home_babip": null,
      "away_babip": 0.324,
      "home_lob": null,
      "away_lob": 62.5,
      "away_road_days": 1,
      "away_tz_cross": null,
      "home_wpct": null,
      "away_road_wpct": null,
      "home_l10_wpct": 0.4,
      "away_l10_wpct": 0.5,
      "home_lineup": [],
      "away_lineup": []
    },
    {
      "tier": "⭐ 穩定",
      "btype": "獨贏",
      "away": "marlins",
      "home": "rays",
      "away_cn": "馬林魚",
      "home_cn": "光芒",
      "bet_label": "光芒 獨贏",
      "bk": "BetOnline.ag",
      "bp": 1.73,
      "con_p": 1.708,
      "dv_p": 0.5638,
      "edge": 14.0,
      "conf": 82.0,
      "stake": 13.0,
      "model_p": 70.4,
      "away_sp": "Sandy Alcantara",
      "home_sp": "Nick Martinez",
      "away_era": 3.92,
      "home_era": 2.1,
      "away_fip": 2.91,
      "home_fip": 2.52,
      "away_k9": 6.7,
      "home_k9": 5.8,
      "away_avgip": 5.4,
      "home_avgip": 5.7,
      "away_whip": 1.68,
      "home_whip": 0.99,
      "away_rest": null,
      "home_rest": null,
      "away_rs": 5.0,
      "home_rs": 3.33,
      "away_rpg": 4.25,
      "home_rpg": 4.48,
      "pred_away": 3.4,
      "pred_home": 4.7,
      "model_total": null,
      "market_total": null,
      "park_factor": 0.95,
      "weather_factor": null,
      "ump_name": null,
      "ump_adj": null,
      "away_trend": 4.31,
      "home_trend": 0.42,
      "line_clv": 0.33,
      "game_date": "2026-05-17",
      "game_time": "04:11",
      "sp_src": "probable",
      "home_hand": "R",
      "away_hand": "R",
      "home_babip": 0.536,
      "away_babip": 0.513,
      "home_lob": 89.5,
      "away_lob": 59.3,
      "away_road_days": 4,
      "away_tz_cross": null,
      "home_wpct": null,
      "away_road_wpct": null,
      "home_l10_wpct": 0.8,
      "away_l10_wpct": 0.4,
      "home_lineup": [],
      "away_lineup": []
    }
  ],
  "recent_history": [
    {
      "date": "2026-05-17",
      "home": "astros",
      "away": "rangers",
      "home_cn": "太空人",
      "away_cn": "遊騎兵",
      "bet_type": "讓分",
      "label": "+1.5",
      "price": 1.75,
      "stake": 11.2,
      "edge": 16.5,
      "result": null
    },
    {
      "date": "2026-05-17",
      "home": "white sox",
      "away": "cubs",
      "home_cn": "白襪",
      "away_cn": "小熊",
      "bet_type": "讓分",
      "label": "+1.5",
      "price": 1.57,
      "stake": 5.8,
      "edge": 10.8,
      "result": null
    },
    {
      "date": "2026-05-17",
      "home": "angels",
      "away": "dodgers",
      "home_cn": "天使",
      "away_cn": "道奇",
      "bet_type": "讓分",
      "label": "+1.5",
      "price": 1.74,
      "stake": 8.1,
      "edge": 12.1,
      "result": null
    },
    {
      "date": "2026-05-17",
      "home": "rays",
      "away": "marlins",
      "home_cn": "光芒",
      "away_cn": "馬林魚",
      "bet_type": "獨贏",
      "label": "",
      "price": 1.77,
      "stake": 14.3,
      "edge": 13.8,
      "result": null
    },
    {
      "date": "2026-05-17",
      "home": "braves",
      "away": "red sox",
      "home_cn": "勇士",
      "away_cn": "紅襪",
      "bet_type": "獨贏",
      "label": "",
      "price": 1.72,
      "stake": 10.7,
      "edge": 11.6,
      "result": null
    },
    {
      "date": "2026-05-15",
      "home": "dodgers",
      "away": "giants",
      "home_cn": "道奇",
      "away_cn": "巨人",
      "bet_type": "獨贏",
      "label": "",
      "price": 1.59,
      "stake": 10.6,
      "edge": 14.7,
      "result": "W"
    },
    {
      "date": "2026-05-13",
      "home": "red sox",
      "away": "phillies",
      "home_cn": "紅襪",
      "away_cn": "費城人",
      "bet_type": "獨贏",
      "label": "",
      "price": 1.74,
      "stake": 50.0,
      "edge": 14.0,
      "result": "W"
    },
    {
      "date": "2026-05-13",
      "home": "orioles",
      "away": "yankees",
      "home_cn": "金鶯",
      "away_cn": "洋基",
      "bet_type": "獨贏",
      "label": "",
      "price": 1.78,
      "stake": 50.0,
      "edge": 22.7,
      "result": "W"
    },
    {
      "date": "2026-05-12",
      "home": "orioles",
      "away": "yankees",
      "home_cn": "金鶯",
      "away_cn": "洋基",
      "bet_type": "獨贏",
      "label": "",
      "price": 1.68,
      "stake": 50.0,
      "edge": 24.1,
      "result": "L"
    },
    {
      "date": "2026-05-11",
      "home": "white sox",
      "away": "mariners",
      "home_cn": "白襪",
      "away_cn": "水手",
      "bet_type": "讓分",
      "label": "+1.5",
      "price": 1.69,
      "stake": 50.0,
      "edge": 14.7,
      "result": "W"
    }
  ],
  "live_games": [],
  "game_preds": {
    "tigers|blue jays": {
      "home_win_prob": 0.6344,
      "market_total": 8.5
    },
    "cardinals|royals": {
      "home_win_prob": 0.658,
      "market_total": 9.0
    },
    "rockies|diamondbacks": {
      "home_win_prob": 0.22,
      "market_total": 11.5
    },
    "nationals|orioles": {
      "home_win_prob": 0.4858,
      "market_total": 10.0
    },
    "pirates|phillies": {
      "home_win_prob": 0.3563,
      "market_total": 8.5
    },
    "rays|marlins": {
      "home_win_prob": 0.7038,
      "market_total": 7.5
    },
    "guardians|reds": {
      "home_win_prob": 0.7295,
      "market_total": 8.5
    },
    "white sox|cubs": {
      "home_win_prob": 0.6202,
      "market_total": 8.5
    },
    "astros|rangers": {
      "home_win_prob": 0.5856,
      "market_total": 8.0
    },
    "twins|brewers": {
      "home_win_prob": 0.3773,
      "market_total": 8.5
    },
    "braves|red sox": {
      "home_win_prob": 0.6737,
      "market_total": 7.5
    },
    "mets|yankees": {
      "home_win_prob": 0.5811,
      "market_total": 8.5
    },
    "mariners|padres": {
      "home_win_prob": 0.5388,
      "market_total": 7.0
    },
    "angels|dodgers": {
      "home_win_prob": 0.3552,
      "market_total": 8.5
    },
    "athletics|giants": {
      "home_win_prob": 0.605,
      "market_total": 9.5
    }
  }
}