{
  "updated": "2026-07-15",
  "season": 2026,
  "al": [
    {
      "division": "American League East",
      "division_cn": "美聯東區",
      "teams": [
        {
          "rank": 3,
          "team_id": 139,
          "team": "Tampa Bay Rays",
          "team_cn": "光芒",
          "abbr": "TB",
          "w": 56,
          "l": 38,
          "pct": 0.596,
          "gb": "-",
          "rs": 425,
          "ra": 393,
          "diff": 32,
          "l10": "5-5",
          "strk": "L1",
          "home": "35-15",
          "away": "21-23"
        },
        {
          "rank": 5,
          "team_id": 147,
          "team": "New York Yankees",
          "team_cn": "洋基",
          "abbr": "NYY",
          "w": 54,
          "l": 42,
          "pct": 0.563,
          "gb": "3.0",
          "rs": 462,
          "ra": 371,
          "diff": 91,
          "l10": "6-4",
          "strk": "W4",
          "home": "23-20",
          "away": "31-22"
        },
        {
          "rank": 19,
          "team_id": 111,
          "team": "Boston Red Sox",
          "team_cn": "紅襪",
          "abbr": "BOS",
          "w": 46,
          "l": 48,
          "pct": 0.489,
          "gb": "10.0",
          "rs": 385,
          "ra": 358,
          "diff": 27,
          "l10": "9-1",
          "strk": "W9",
          "home": "17-27",
          "away": "29-21"
        },
        {
          "rank": 21,
          "team_id": 110,
          "team": "Baltimore Orioles",
          "team_cn": "金鶯",
          "abbr": "BAL",
          "w": 46,
          "l": 51,
          "pct": 0.474,
          "gb": "11.5",
          "rs": 447,
          "ra": 466,
          "diff": -19,
          "l10": "7-3",
          "strk": "W4",
          "home": "28-25",
          "away": "18-26"
        },
        {
          "rank": 22,
          "team_id": 141,
          "team": "Toronto Blue Jays",
          "team_cn": "藍鳥",
          "abbr": "TOR",
          "w": 45,
          "l": 51,
          "pct": 0.469,
          "gb": "12.0",
          "rs": 392,
          "ra": 427,
          "diff": -35,
          "l10": "5-5",
          "strk": "L2",
          "home": "24-25",
          "away": "21-26"
        }
      ]
    },
    {
      "division": "American League Central",
      "division_cn": "美聯中區",
      "teams": [
        {
          "rank": 10,
          "team_id": 145,
          "team": "Chicago White Sox",
          "team_cn": "白襪",
          "abbr": "CWS",
          "w": 50,
          "l": 45,
          "pct": 0.526,
          "gb": "-",
          "rs": 454,
          "ra": 419,
          "diff": 35,
          "l10": "5-5",
          "strk": "W3",
          "home": "31-17",
          "away": "19-28"
        },
        {
          "rank": 9,
          "team_id": 114,
          "team": "Cleveland Guardians",
          "team_cn": "守護者",
          "abbr": "CLE",
          "w": 51,
          "l": 46,
          "pct": 0.526,
          "gb": "-",
          "rs": 385,
          "ra": 387,
          "diff": -2,
          "l10": "6-4",
          "strk": "W4",
          "home": "24-22",
          "away": "27-24"
        },
        {
          "rank": 16,
          "team_id": 142,
          "team": "Minnesota Twins",
          "team_cn": "雙城",
          "abbr": "MIN",
          "w": 48,
          "l": 49,
          "pct": 0.495,
          "gb": "3.0",
          "rs": 471,
          "ra": 485,
          "diff": -14,
          "l10": "7-3",
          "strk": "W2",
          "home": "26-25",
          "away": "22-24"
        },
        {
          "rank": 23,
          "team_id": 116,
          "team": "Detroit Tigers",
          "team_cn": "老虎",
          "abbr": "DET",
          "w": 44,
          "l": 52,
          "pct": 0.458,
          "gb": "6.5",
          "rs": 407,
          "ra": 383,
          "diff": 24,
          "l10": "7-3",
          "strk": "L2",
          "home": "27-23",
          "away": "17-29"
        },
        {
          "rank": 29,
          "team_id": 118,
          "team": "Kansas City Royals",
          "team_cn": "皇家",
          "abbr": "KC",
          "w": 38,
          "l": 59,
          "pct": 0.392,
          "gb": "13.0",
          "rs": 411,
          "ra": 499,
          "diff": -88,
          "l10": "3-7",
          "strk": "L5",
          "home": "21-26",
          "away": "17-33"
        }
      ]
    },
    {
      "division": "American League West",
      "division_cn": "美聯西區",
      "teams": [
        {
          "rank": 13,
          "team_id": 140,
          "team": "Texas Rangers",
          "team_cn": "遊騎兵",
          "abbr": "TEX",
          "w": 49,
          "l": 47,
          "pct": 0.51,
          "gb": "-",
          "rs": 399,
          "ra": 414,
          "diff": -15,
          "l10": "5-5",
          "strk": "W1",
          "home": "24-22",
          "away": "25-25"
        },
        {
          "rank": 17,
          "team_id": 136,
          "team": "Seattle Mariners",
          "team_cn": "水手",
          "abbr": "SEA",
          "w": 48,
          "l": 49,
          "pct": 0.495,
          "gb": "1.5",
          "rs": 392,
          "ra": 376,
          "diff": 16,
          "l10": "4-6",
          "strk": "W1",
          "home": "27-20",
          "away": "21-29"
        },
        {
          "rank": 20,
          "team_id": 117,
          "team": "Houston Astros",
          "team_cn": "太空人",
          "abbr": "HOU",
          "w": 47,
          "l": 51,
          "pct": 0.48,
          "gb": "3.0",
          "rs": 449,
          "ra": 496,
          "diff": -47,
          "l10": "4-6",
          "strk": "L1",
          "home": "23-24",
          "away": "24-27"
        },
        {
          "rank": 25,
          "team_id": 133,
          "team": "Athletics",
          "team_cn": "Athletics",
          "abbr": "ATH",
          "w": 41,
          "l": 55,
          "pct": 0.427,
          "gb": "8.0",
          "rs": 422,
          "ra": 528,
          "diff": -106,
          "l10": "1-9",
          "strk": "L9",
          "home": "19-28",
          "away": "22-27"
        },
        {
          "rank": 30,
          "team_id": 108,
          "team": "Los Angeles Angels",
          "team_cn": "天使",
          "abbr": "LAA",
          "w": 38,
          "l": 59,
          "pct": 0.392,
          "gb": "11.5",
          "rs": 430,
          "ra": 485,
          "diff": -55,
          "l10": "2-8",
          "strk": "L2",
          "home": "21-25",
          "away": "17-34"
        }
      ]
    }
  ],
  "nl": [
    {
      "division": "National League East",
      "division_cn": "國聯東區",
      "teams": [
        {
          "rank": 4,
          "team_id": 144,
          "team": "Atlanta Braves",
          "team_cn": "勇士",
          "abbr": "ATL",
          "w": 55,
          "l": 40,
          "pct": 0.579,
          "gb": "-",
          "rs": 460,
          "ra": 368,
          "diff": 92,
          "l10": "5-5",
          "strk": "W1",
          "home": "27-18",
          "away": "28-22"
        },
        {
          "rank": 7,
          "team_id": 143,
          "team": "Philadelphia Phillies",
          "team_cn": "費城人",
          "abbr": "PHI",
          "w": 54,
          "l": 43,
          "pct": 0.557,
          "gb": "2.0",
          "rs": 424,
          "ra": 434,
          "diff": -10,
          "l10": "5-5",
          "strk": "W2",
          "home": "25-21",
          "away": "29-22"
        },
        {
          "rank": 8,
          "team_id": 146,
          "team": "Miami Marlins",
          "team_cn": "馬林魚",
          "abbr": "MIA",
          "w": 52,
          "l": 45,
          "pct": 0.536,
          "gb": "4.0",
          "rs": 439,
          "ra": 415,
          "diff": 24,
          "l10": "6-4",
          "strk": "L3",
          "home": "31-20",
          "away": "21-25"
        },
        {
          "rank": 18,
          "team_id": 120,
          "team": "Washington Nationals",
          "team_cn": "國民",
          "abbr": "WSH",
          "w": 48,
          "l": 49,
          "pct": 0.495,
          "gb": "8.0",
          "rs": 516,
          "ra": 509,
          "diff": 7,
          "l10": "4-6",
          "strk": "L3",
          "home": "20-31",
          "away": "28-18"
        },
        {
          "rank": 27,
          "team_id": 121,
          "team": "New York Mets",
          "team_cn": "大都會",
          "abbr": "NYM",
          "w": 40,
          "l": 57,
          "pct": 0.412,
          "gb": "16.0",
          "rs": 398,
          "ra": 463,
          "diff": -65,
          "l10": "4-6",
          "strk": "L3",
          "home": "21-28",
          "away": "19-29"
        }
      ]
    },
    {
      "division": "National League Central",
      "division_cn": "國聯中區",
      "teams": [
        {
          "rank": 2,
          "team_id": 158,
          "team": "Milwaukee Brewers",
          "team_cn": "釀酒人",
          "abbr": "MIL",
          "w": 59,
          "l": 37,
          "pct": 0.615,
          "gb": "-",
          "rs": 489,
          "ra": 363,
          "diff": 126,
          "l10": "5-5",
          "strk": "L3",
          "home": "29-18",
          "away": "30-19"
        },
        {
          "rank": 6,
          "team_id": 112,
          "team": "Chicago Cubs",
          "team_cn": "小熊",
          "abbr": "CHC",
          "w": 54,
          "l": 42,
          "pct": 0.563,
          "gb": "5.0",
          "rs": 484,
          "ra": 432,
          "diff": 52,
          "l10": "6-4",
          "strk": "W2",
          "home": "27-19",
          "away": "27-23"
        },
        {
          "rank": 11,
          "team_id": 138,
          "team": "St. Louis Cardinals",
          "team_cn": "紅雀",
          "abbr": "STL",
          "w": 50,
          "l": 45,
          "pct": 0.526,
          "gb": "8.5",
          "rs": 429,
          "ra": 423,
          "diff": 6,
          "l10": "4-6",
          "strk": "L1",
          "home": "26-26",
          "away": "24-19"
        },
        {
          "rank": 12,
          "team_id": 134,
          "team": "Pittsburgh Pirates",
          "team_cn": "海盜",
          "abbr": "PIT",
          "w": 50,
          "l": 47,
          "pct": 0.515,
          "gb": "9.5",
          "rs": 516,
          "ra": 472,
          "diff": 44,
          "l10": "7-3",
          "strk": "W3",
          "home": "27-24",
          "away": "23-23"
        },
        {
          "rank": 24,
          "team_id": 113,
          "team": "Cincinnati Reds",
          "team_cn": "紅人",
          "abbr": "CIN",
          "w": 43,
          "l": 52,
          "pct": 0.453,
          "gb": "15.5",
          "rs": 395,
          "ra": 455,
          "diff": -60,
          "l10": "4-6",
          "strk": "L2",
          "home": "22-28",
          "away": "21-24"
        }
      ]
    },
    {
      "division": "National League West",
      "division_cn": "國聯西區",
      "teams": [
        {
          "rank": 1,
          "team_id": 119,
          "team": "Los Angeles Dodgers",
          "team_cn": "道奇",
          "abbr": "LAD",
          "w": 61,
          "l": 36,
          "pct": 0.629,
          "gb": "-",
          "rs": 506,
          "ra": 357,
          "diff": 149,
          "l10": "5-5",
          "strk": "L3",
          "home": "31-19",
          "away": "30-17"
        },
        {
          "rank": 14,
          "team_id": 109,
          "team": "Arizona Diamondbacks",
          "team_cn": "響尾蛇",
          "abbr": "ARI",
          "w": 49,
          "l": 47,
          "pct": 0.51,
          "gb": "11.5",
          "rs": 416,
          "ra": 429,
          "diff": -13,
          "l10": "6-4",
          "strk": "W4",
          "home": "27-20",
          "away": "22-27"
        },
        {
          "rank": 15,
          "team_id": 135,
          "team": "San Diego Padres",
          "team_cn": "教士",
          "abbr": "SD",
          "w": 48,
          "l": 48,
          "pct": 0.5,
          "gb": "12.5",
          "rs": 379,
          "ra": 422,
          "diff": -43,
          "l10": "5-5",
          "strk": "W2",
          "home": "27-24",
          "away": "21-24"
        },
        {
          "rank": 26,
          "team_id": 137,
          "team": "San Francisco Giants",
          "team_cn": "巨人",
          "abbr": "SF",
          "w": 41,
          "l": 55,
          "pct": 0.427,
          "gb": "19.5",
          "rs": 395,
          "ra": 459,
          "diff": -64,
          "l10": "5-5",
          "strk": "W2",
          "home": "22-25",
          "away": "19-30"
        },
        {
          "rank": 28,
          "team_id": 115,
          "team": "Colorado Rockies",
          "team_cn": "落磯",
          "abbr": "COL",
          "w": 39,
          "l": 59,
          "pct": 0.398,
          "gb": "22.5",
          "rs": 466,
          "ra": 555,
          "diff": -89,
          "l10": "4-6",
          "strk": "L2",
          "home": "22-25",
          "away": "17-34"
        }
      ]
    }
  ],
  "all": [
    {
      "rank": 1,
      "team_id": 119,
      "team": "Los Angeles Dodgers",
      "team_cn": "道奇",
      "abbr": "LAD",
      "w": 61,
      "l": 36,
      "pct": 0.629,
      "gb": "-",
      "rs": 506,
      "ra": 357,
      "diff": 149,
      "l10": "5-5",
      "strk": "L3",
      "home": "31-19",
      "away": "30-17"
    },
    {
      "rank": 2,
      "team_id": 158,
      "team": "Milwaukee Brewers",
      "team_cn": "釀酒人",
      "abbr": "MIL",
      "w": 59,
      "l": 37,
      "pct": 0.615,
      "gb": "-",
      "rs": 489,
      "ra": 363,
      "diff": 126,
      "l10": "5-5",
      "strk": "L3",
      "home": "29-18",
      "away": "30-19"
    },
    {
      "rank": 3,
      "team_id": 139,
      "team": "Tampa Bay Rays",
      "team_cn": "光芒",
      "abbr": "TB",
      "w": 56,
      "l": 38,
      "pct": 0.596,
      "gb": "-",
      "rs": 425,
      "ra": 393,
      "diff": 32,
      "l10": "5-5",
      "strk": "L1",
      "home": "35-15",
      "away": "21-23"
    },
    {
      "rank": 4,
      "team_id": 144,
      "team": "Atlanta Braves",
      "team_cn": "勇士",
      "abbr": "ATL",
      "w": 55,
      "l": 40,
      "pct": 0.579,
      "gb": "-",
      "rs": 460,
      "ra": 368,
      "diff": 92,
      "l10": "5-5",
      "strk": "W1",
      "home": "27-18",
      "away": "28-22"
    },
    {
      "rank": 5,
      "team_id": 147,
      "team": "New York Yankees",
      "team_cn": "洋基",
      "abbr": "NYY",
      "w": 54,
      "l": 42,
      "pct": 0.563,
      "gb": "3.0",
      "rs": 462,
      "ra": 371,
      "diff": 91,
      "l10": "6-4",
      "strk": "W4",
      "home": "23-20",
      "away": "31-22"
    },
    {
      "rank": 6,
      "team_id": 112,
      "team": "Chicago Cubs",
      "team_cn": "小熊",
      "abbr": "CHC",
      "w": 54,
      "l": 42,
      "pct": 0.563,
      "gb": "5.0",
      "rs": 484,
      "ra": 432,
      "diff": 52,
      "l10": "6-4",
      "strk": "W2",
      "home": "27-19",
      "away": "27-23"
    },
    {
      "rank": 7,
      "team_id": 143,
      "team": "Philadelphia Phillies",
      "team_cn": "費城人",
      "abbr": "PHI",
      "w": 54,
      "l": 43,
      "pct": 0.557,
      "gb": "2.0",
      "rs": 424,
      "ra": 434,
      "diff": -10,
      "l10": "5-5",
      "strk": "W2",
      "home": "25-21",
      "away": "29-22"
    },
    {
      "rank": 8,
      "team_id": 146,
      "team": "Miami Marlins",
      "team_cn": "馬林魚",
      "abbr": "MIA",
      "w": 52,
      "l": 45,
      "pct": 0.536,
      "gb": "4.0",
      "rs": 439,
      "ra": 415,
      "diff": 24,
      "l10": "6-4",
      "strk": "L3",
      "home": "31-20",
      "away": "21-25"
    },
    {
      "rank": 9,
      "team_id": 114,
      "team": "Cleveland Guardians",
      "team_cn": "守護者",
      "abbr": "CLE",
      "w": 51,
      "l": 46,
      "pct": 0.526,
      "gb": "-",
      "rs": 385,
      "ra": 387,
      "diff": -2,
      "l10": "6-4",
      "strk": "W4",
      "home": "24-22",
      "away": "27-24"
    },
    {
      "rank": 10,
      "team_id": 145,
      "team": "Chicago White Sox",
      "team_cn": "白襪",
      "abbr": "CWS",
      "w": 50,
      "l": 45,
      "pct": 0.526,
      "gb": "-",
      "rs": 454,
      "ra": 419,
      "diff": 35,
      "l10": "5-5",
      "strk": "W3",
      "home": "31-17",
      "away": "19-28"
    },
    {
      "rank": 11,
      "team_id": 138,
      "team": "St. Louis Cardinals",
      "team_cn": "紅雀",
      "abbr": "STL",
      "w": 50,
      "l": 45,
      "pct": 0.526,
      "gb": "8.5",
      "rs": 429,
      "ra": 423,
      "diff": 6,
      "l10": "4-6",
      "strk": "L1",
      "home": "26-26",
      "away": "24-19"
    },
    {
      "rank": 12,
      "team_id": 134,
      "team": "Pittsburgh Pirates",
      "team_cn": "海盜",
      "abbr": "PIT",
      "w": 50,
      "l": 47,
      "pct": 0.515,
      "gb": "9.5",
      "rs": 516,
      "ra": 472,
      "diff": 44,
      "l10": "7-3",
      "strk": "W3",
      "home": "27-24",
      "away": "23-23"
    },
    {
      "rank": 13,
      "team_id": 140,
      "team": "Texas Rangers",
      "team_cn": "遊騎兵",
      "abbr": "TEX",
      "w": 49,
      "l": 47,
      "pct": 0.51,
      "gb": "-",
      "rs": 399,
      "ra": 414,
      "diff": -15,
      "l10": "5-5",
      "strk": "W1",
      "home": "24-22",
      "away": "25-25"
    },
    {
      "rank": 14,
      "team_id": 109,
      "team": "Arizona Diamondbacks",
      "team_cn": "響尾蛇",
      "abbr": "ARI",
      "w": 49,
      "l": 47,
      "pct": 0.51,
      "gb": "11.5",
      "rs": 416,
      "ra": 429,
      "diff": -13,
      "l10": "6-4",
      "strk": "W4",
      "home": "27-20",
      "away": "22-27"
    },
    {
      "rank": 15,
      "team_id": 135,
      "team": "San Diego Padres",
      "team_cn": "教士",
      "abbr": "SD",
      "w": 48,
      "l": 48,
      "pct": 0.5,
      "gb": "12.5",
      "rs": 379,
      "ra": 422,
      "diff": -43,
      "l10": "5-5",
      "strk": "W2",
      "home": "27-24",
      "away": "21-24"
    },
    {
      "rank": 16,
      "team_id": 142,
      "team": "Minnesota Twins",
      "team_cn": "雙城",
      "abbr": "MIN",
      "w": 48,
      "l": 49,
      "pct": 0.495,
      "gb": "3.0",
      "rs": 471,
      "ra": 485,
      "diff": -14,
      "l10": "7-3",
      "strk": "W2",
      "home": "26-25",
      "away": "22-24"
    },
    {
      "rank": 17,
      "team_id": 136,
      "team": "Seattle Mariners",
      "team_cn": "水手",
      "abbr": "SEA",
      "w": 48,
      "l": 49,
      "pct": 0.495,
      "gb": "1.5",
      "rs": 392,
      "ra": 376,
      "diff": 16,
      "l10": "4-6",
      "strk": "W1",
      "home": "27-20",
      "away": "21-29"
    },
    {
      "rank": 18,
      "team_id": 120,
      "team": "Washington Nationals",
      "team_cn": "國民",
      "abbr": "WSH",
      "w": 48,
      "l": 49,
      "pct": 0.495,
      "gb": "8.0",
      "rs": 516,
      "ra": 509,
      "diff": 7,
      "l10": "4-6",
      "strk": "L3",
      "home": "20-31",
      "away": "28-18"
    },
    {
      "rank": 19,
      "team_id": 111,
      "team": "Boston Red Sox",
      "team_cn": "紅襪",
      "abbr": "BOS",
      "w": 46,
      "l": 48,
      "pct": 0.489,
      "gb": "10.0",
      "rs": 385,
      "ra": 358,
      "diff": 27,
      "l10": "9-1",
      "strk": "W9",
      "home": "17-27",
      "away": "29-21"
    },
    {
      "rank": 20,
      "team_id": 117,
      "team": "Houston Astros",
      "team_cn": "太空人",
      "abbr": "HOU",
      "w": 47,
      "l": 51,
      "pct": 0.48,
      "gb": "3.0",
      "rs": 449,
      "ra": 496,
      "diff": -47,
      "l10": "4-6",
      "strk": "L1",
      "home": "23-24",
      "away": "24-27"
    },
    {
      "rank": 21,
      "team_id": 110,
      "team": "Baltimore Orioles",
      "team_cn": "金鶯",
      "abbr": "BAL",
      "w": 46,
      "l": 51,
      "pct": 0.474,
      "gb": "11.5",
      "rs": 447,
      "ra": 466,
      "diff": -19,
      "l10": "7-3",
      "strk": "W4",
      "home": "28-25",
      "away": "18-26"
    },
    {
      "rank": 22,
      "team_id": 141,
      "team": "Toronto Blue Jays",
      "team_cn": "藍鳥",
      "abbr": "TOR",
      "w": 45,
      "l": 51,
      "pct": 0.469,
      "gb": "12.0",
      "rs": 392,
      "ra": 427,
      "diff": -35,
      "l10": "5-5",
      "strk": "L2",
      "home": "24-25",
      "away": "21-26"
    },
    {
      "rank": 23,
      "team_id": 116,
      "team": "Detroit Tigers",
      "team_cn": "老虎",
      "abbr": "DET",
      "w": 44,
      "l": 52,
      "pct": 0.458,
      "gb": "6.5",
      "rs": 407,
      "ra": 383,
      "diff": 24,
      "l10": "7-3",
      "strk": "L2",
      "home": "27-23",
      "away": "17-29"
    },
    {
      "rank": 24,
      "team_id": 113,
      "team": "Cincinnati Reds",
      "team_cn": "紅人",
      "abbr": "CIN",
      "w": 43,
      "l": 52,
      "pct": 0.453,
      "gb": "15.5",
      "rs": 395,
      "ra": 455,
      "diff": -60,
      "l10": "4-6",
      "strk": "L2",
      "home": "22-28",
      "away": "21-24"
    },
    {
      "rank": 25,
      "team_id": 133,
      "team": "Athletics",
      "team_cn": "Athletics",
      "abbr": "ATH",
      "w": 41,
      "l": 55,
      "pct": 0.427,
      "gb": "8.0",
      "rs": 422,
      "ra": 528,
      "diff": -106,
      "l10": "1-9",
      "strk": "L9",
      "home": "19-28",
      "away": "22-27"
    },
    {
      "rank": 26,
      "team_id": 137,
      "team": "San Francisco Giants",
      "team_cn": "巨人",
      "abbr": "SF",
      "w": 41,
      "l": 55,
      "pct": 0.427,
      "gb": "19.5",
      "rs": 395,
      "ra": 459,
      "diff": -64,
      "l10": "5-5",
      "strk": "W2",
      "home": "22-25",
      "away": "19-30"
    },
    {
      "rank": 27,
      "team_id": 121,
      "team": "New York Mets",
      "team_cn": "大都會",
      "abbr": "NYM",
      "w": 40,
      "l": 57,
      "pct": 0.412,
      "gb": "16.0",
      "rs": 398,
      "ra": 463,
      "diff": -65,
      "l10": "4-6",
      "strk": "L3",
      "home": "21-28",
      "away": "19-29"
    },
    {
      "rank": 28,
      "team_id": 115,
      "team": "Colorado Rockies",
      "team_cn": "落磯",
      "abbr": "COL",
      "w": 39,
      "l": 59,
      "pct": 0.398,
      "gb": "22.5",
      "rs": 466,
      "ra": 555,
      "diff": -89,
      "l10": "4-6",
      "strk": "L2",
      "home": "22-25",
      "away": "17-34"
    },
    {
      "rank": 29,
      "team_id": 118,
      "team": "Kansas City Royals",
      "team_cn": "皇家",
      "abbr": "KC",
      "w": 38,
      "l": 59,
      "pct": 0.392,
      "gb": "13.0",
      "rs": 411,
      "ra": 499,
      "diff": -88,
      "l10": "3-7",
      "strk": "L5",
      "home": "21-26",
      "away": "17-33"
    },
    {
      "rank": 30,
      "team_id": 108,
      "team": "Los Angeles Angels",
      "team_cn": "天使",
      "abbr": "LAA",
      "w": 38,
      "l": 59,
      "pct": 0.392,
      "gb": "11.5",
      "rs": 430,
      "ra": 485,
      "diff": -55,
      "l10": "2-8",
      "strk": "L2",
      "home": "21-25",
      "away": "17-34"
    }
  ]
}